{
  	"qcfpunch:Defend_Weakest": {
    	"NAME": "“最强流”防御",
    	"DESCRIPTION": "消耗。 NL 获得 !B! 点 格挡 。 NL 虚无 。"
  	},

	"qcfpunch:Strike_Weakest": {
    	"NAME": "“最强流”打击",
    	"DESCRIPTION": "消耗。 NL 造成 !D! 点 伤害 。 NL 虚无 。"
  	},
  	
	"qcfpunch:WeakestEnergyBlast": {
    	"NAME": "“最强流”波动",
    	"DESCRIPTION": "消耗。 NL 造成 !D! 点 伤害 。 NL 获得 1/3  qcfpunch:怒气槽 。  NL 虚无 。"
	},
	
	"qcfpunch:WeakestFlyingKick": {
    	"NAME": "“最强流”飞燕脚",
    	"DESCRIPTION": "消耗。 NL 造成 !D! 点 伤害 。 NL 虚无 。"
	},

	"qcfpunch:WeakestProvocation": {
    	"NAME": "“最强流”挑衅",
    	"DESCRIPTION": "消耗。 NL 给予 1 层 易伤 。 NL 获得 1/3 qcfpunch:怒气槽 。 NL 虚无 。"
	},
	
	"qcfpunch:WeakestTaunt": {
    	"NAME": "“最强流”嘲讽",
    	"DESCRIPTION": "消耗。 NL 给予 1 层 虚弱 。 NL Gain 1/3 qcfpunch:怒气槽 。 NL 虚无 。"
	},

	"WWWWWWWWWWWW": {
    	"NAME": "WWWWWWWWWWWWWW",
    	"DESCRIPTION": "WWWWWWWWWWWWWWWWWWWWWWWWWWWWWWW"
	}
}